{
  "fecha_actualizacion": "2026-03-26 03:10:42",
  "total_sorteos": 13,
  "sorteos": {
    "juga3_11am": {
      "juego": "juga3_11am",
      "nombre_juego": "Jugá 3 11:00 AM",
      "fecha_consulta": "2026-03-25 17:10:26",
      "fecha_sorteo": "25-03",
      "hora_sorteo": "11:00 AM",
      "numero_ganador": "288",
      "numeros_individuales": [
        "2",
        "8",
        "8"
      ],
      "numeros_adicionales": [
        "288"
      ],
      "serie": null,
      "folio": null,
      "estado": "completado",
      "logo_url": "/logos/juga3.png",
      "extras": {}
    },
    "juga3_3pm": {
      "juego": "juga3_3pm",
      "nombre_juego": "Jugá 3 3:00 PM",
      "fecha_consulta": "2026-03-25 21:10:28",
      "fecha_sorteo": "25-03",
      "hora_sorteo": "3:00 PM",
      "numero_ganador": "008",
      "numeros_individuales": [
        "0",
        "0",
        "8"
      ],
      "numeros_adicionales": [
        "008"
      ],
      "serie": null,
      "folio": null,
      "estado": "completado",
      "logo_url": "/logos/juga3.png",
      "extras": {}
    },
    "juga3_9pm": {
      "juego": "juga3_9pm",
      "nombre_juego": "Jugá 3 9:00 PM",
      "fecha_consulta": "2026-03-26 03:10:25",
      "fecha_sorteo": "25-03",
      "hora_sorteo": "9:00 PM",
      "numero_ganador": "674",
      "numeros_individuales": [
        "6",
        "7",
        "4"
      ],
      "numeros_adicionales": [
        "674"
      ],
      "serie": null,
      "folio": null,
      "estado": "completado",
      "logo_url": "/logos/juga3.png",
      "extras": {}
    },
    "premia2_10am": {
      "juego": "premia2_10am",
      "nombre_juego": "Premia 2 11:00 AM",
      "fecha_consulta": "2026-03-25 17:10:29",
      "fecha_sorteo": "25-03",
      "hora_sorteo": "11:00 AM",
      "numero_ganador": "83",
      "numeros_individuales": [
        "83",
        "78"
      ],
      "numeros_adicionales": [
        "83",
        "78"
      ],
      "serie": null,
      "folio": null,
      "estado": "completado",
      "logo_url": "/logos/premia2.png",
      "extras": {}
    },
    "premia2_2pm": {
      "juego": "premia2_2pm",
      "nombre_juego": "Premia 2 3:00 PM",
      "fecha_consulta": "2026-03-25 21:10:31",
      "fecha_sorteo": "25-03",
      "hora_sorteo": "3:00 PM",
      "numero_ganador": "79",
      "numeros_individuales": [
        "79",
        "33"
      ],
      "numeros_adicionales": [
        "79",
        "33"
      ],
      "serie": null,
      "folio": null,
      "estado": "completado",
      "logo_url": "/logos/premia2.png",
      "extras": {}
    },
    "premia2_9pm": {
      "juego": "premia2_9pm",
      "nombre_juego": "Premia 2 9:00 PM",
      "fecha_consulta": "2026-03-26 03:10:29",
      "fecha_sorteo": "25-03",
      "hora_sorteo": "9:00 PM",
      "numero_ganador": "20",
      "numeros_individuales": [
        "20",
        "55"
      ],
      "numeros_adicionales": [
        "20",
        "55"
      ],
      "serie": null,
      "folio": null,
      "estado": "completado",
      "logo_url": "/logos/premia2.png",
      "extras": {}
    },
    "pega3_10am": {
      "juego": "pega3_10am",
      "nombre_juego": "Pega 3 11:00 AM",
      "fecha_consulta": "2026-03-25 17:10:32",
      "fecha_sorteo": "25-03",
      "hora_sorteo": "11:00 AM",
      "numero_ganador": "30",
      "numeros_individuales": [
        "30",
        "69",
        "01"
      ],
      "numeros_adicionales": [
        "30",
        "69",
        "01"
      ],
      "serie": null,
      "folio": null,
      "estado": "completado",
      "logo_url": "/logos/pega3.png",
      "extras": {}
    },
    "pega3_2pm": {
      "juego": "pega3_2pm",
      "nombre_juego": "Pega 3 3:00 PM",
      "fecha_consulta": "2026-03-25 21:10:35",
      "fecha_sorteo": "25-03",
      "hora_sorteo": "3:00 PM",
      "numero_ganador": "00",
      "numeros_individuales": [
        "00",
        "69",
        "48"
      ],
      "numeros_adicionales": [
        "00",
        "69",
        "48"
      ],
      "serie": null,
      "folio": null,
      "estado": "completado",
      "logo_url": "/logos/pega3.png",
      "extras": {}
    },
    "pega3_9pm": {
      "juego": "pega3_9pm",
      "nombre_juego": "Pega 3 9:00 PM",
      "fecha_consulta": "2026-03-26 03:10:32",
      "fecha_sorteo": "25-03",
      "hora_sorteo": "9:00 PM",
      "numero_ganador": "10",
      "numeros_individuales": [
        "10",
        "62",
        "96"
      ],
      "numeros_adicionales": [
        "10",
        "62",
        "96"
      ],
      "serie": null,
      "folio": null,
      "estado": "completado",
      "logo_url": "/logos/pega3.png",
      "extras": {}
    },
    "la_diaria_10am": {
      "juego": "la_diaria_10am",
      "nombre_juego": "La Diaria 11:00 AM",
      "fecha_consulta": "2026-03-25 17:10:36",
      "fecha_sorteo": "25-03",
      "hora_sorteo": "11:00 AM",
      "numero_ganador": "52",
      "numeros_individuales": [
        "52",
        "Zorrillo",
        "2X"
      ],
      "numeros_adicionales": [
        "52",
        "Zorrillo",
        "2X"
      ],
      "serie": null,
      "folio": null,
      "estado": "completado",
      "logo_url": "/logos/la_diaria.png",
      "extras": {}
    },
    "la_diaria_2pm": {
      "juego": "la_diaria_2pm",
      "nombre_juego": "La Diaria 3:00 PM",
      "fecha_consulta": "2026-03-25 21:10:38",
      "fecha_sorteo": "25-03",
      "hora_sorteo": "3:00 PM",
      "numero_ganador": "83",
      "numeros_individuales": [
        "83",
        "Bote",
        "2X"
      ],
      "numeros_adicionales": [
        "83",
        "Bote",
        "2X"
      ],
      "serie": null,
      "folio": null,
      "estado": "completado",
      "logo_url": "/logos/la_diaria.png",
      "extras": {}
    },
    "la_diaria_9pm": {
      "juego": "la_diaria_9pm",
      "nombre_juego": "La Diaria 9:00 PM",
      "fecha_consulta": "2026-03-26 03:10:36",
      "fecha_sorteo": "25-03",
      "hora_sorteo": "9:00 PM",
      "numero_ganador": "96",
      "numeros_individuales": [
        "96",
        "Dinero",
        "JG"
      ],
      "numeros_adicionales": [
        "96",
        "Dinero",
        "JG"
      ],
      "serie": null,
      "folio": null,
      "estado": "completado",
      "logo_url": "/logos/la_diaria.png",
      "extras": {}
    },
    "super_premio": {
      "juego": "super_premio",
      "nombre_juego": "Super Premio",
      "fecha_consulta": "2026-03-26 03:10:39",
      "fecha_sorteo": "25-03",
      "hora_sorteo": null,
      "numero_ganador": "06",
      "numeros_individuales": [
        "06",
        "01",
        "19",
        "26",
        "29",
        "12"
      ],
      "numeros_adicionales": [
        "06",
        "01",
        "19",
        "26",
        "29",
        "12"
      ],
      "serie": null,
      "folio": null,
      "estado": "completado",
      "logo_url": "/logos/super_premio.png",
      "extras": {}
    }
  }
}